gurlon/__init__.py
gurlon/dynamodb.py
gurlon/processor.py
gurlon/py.typed
gurlon/s3.py
gurlon-0.3.0.dist-info/METADATA
gurlon-0.3.0.dist-info/WHEEL
gurlon-0.3.0.dist-info/entry_points.txt
gurlon-0.3.0.dist-info/licenses/LICENSE
gurlon-0.3.0.dist-info/RECORD
