Metadata-Version: 2.3
Name: gurlon
Version: 0.3.0
Summary: Transform unstructured DynamoDB data into local SQL tables.
Author-email: Zach Fuller <zach.fuller1222@gmail.com>
License: MIT
Requires-Python: >=3.12
Requires-Dist: boto3>=1.35.68
Requires-Dist: duckdb>=1.1.3
Requires-Dist: dynamodb-json>=1.4.2
Requires-Dist: orjson>=3.10.12
Requires-Dist: pydantic>=2.10.1
Requires-Dist: sqlmodel>=0.0.22
Requires-Dist: structlog>=24.4.0
